ariadne/__init__.py
ariadne/ariadne.py
ariadne/endtoend_tests.py
ariadne/unittests.py
ariadne_lib-0.4.0.dist-info/METADATA
ariadne_lib-0.4.0.dist-info/WHEEL
ariadne_lib-0.4.0.dist-info/entry_points.txt
ariadne_lib-0.4.0.dist-info/licenses/LICENSE
ariadne_lib-0.4.0.dist-info/RECORD
