Metadata-Version: 2.4
Name: ariadne-lib
Version: 0.4.0
Summary: Find your way in a maze of experiments
Project-URL: Repository, https://github.com/chentoast/ariadne.git
Author: Tony Chen
License-File: LICENSE
Requires-Python: >=3.12
